population_error/__init__.py
population_error/_version.py
population_error/statistics.py
population_error-0.2.2.dist-info/METADATA
population_error-0.2.2.dist-info/WHEEL
population_error-0.2.2.dist-info/top_level.txt
population_error-0.2.2.dist-info/RECORD
