Metadata-Version: 2.4
Name: population-error
Version: 0.2.2
Summary: JAX-based package for estimating the information lost due to Monte Carlo approximations in GW population inference.
Author-email: Jack Heinzel <heinzelj@mit.edu>
Project-URL: Source, https://github.com/jack-heinzel/population-error
Project-URL: Documentation, https://population-error.readthedocs.io/
Classifier: License :: OSI Approved :: MIT License
Classifier: Programming Language :: Python :: 3
Requires-Python: >=3.9
Requires-Dist: jax
Requires-Dist: jax_tqdm
Requires-Dist: gwpopulation
Requires-Dist: bilby
